{
  "domain": "音乐",
  "description": "音乐播放相关规则（使用可复用词汇组）",
  "patterns": [
    {
      "pattern": "{{action_play}}(?P<target>.+)(的)?({{target_music_related}})",
      "intent": "music",
      "action": "play",
      "target": null,
      "confidence": 0.90,
      "group_names": ["action", "target"]
    },
    {
      "pattern": "{{action_control_music}}",
      "intent": "music",
      "action": "control",
      "target": null,
      "confidence": 0.95
    },
    {
      "pattern": "{{action_adjust_volume}}(?P<target>{{target_volume}})",
      "intent": "music",
      "action": "adjust",
      "target": null,
      "confidence": 0.90,
      "group_names": ["action", "target"]
    },
    {
      "pattern": "{{action_music_mode}}",
      "intent": "music",
      "action": "mode",
      "target": null,
      "confidence": 0.95
    },
    {
      "pattern": "{{action_search}}(?P<target>.+)(的)?({{target_music_related}})",
      "intent": "music",
      "action": "search",
      "target": null,
      "confidence": 0.85,
      "group_names": ["action", "target"]
    }
  ]
}
